dbpedia_get/__init__.py
dbpedia_get/lookup/__init__.py
dbpedia_get/lookup/bp/__init__.py
dbpedia_get/lookup/bp/lookup_orchestrator.py
dbpedia_get/lookup/dmo/__init__.py
dbpedia_get/lookup/dmo/dbpedia_content_normalizer.py
dbpedia_get/lookup/dmo/dbpedia_page_finder.py
dbpedia_get/lookup/dmo/page_cache_entry.py
dbpedia_get/lookup/dmo/page_cache_io.py
dbpedia_get/lookup/dmo/page_cache_reader.py
dbpedia_get/lookup/dmo/page_title_path.py
dbpedia_get/lookup/dto/__init__.py
dbpedia_get/lookup/dto/wikipedia_page_status.py
dbpedia_get/lookup/README.md
dbpedia_get/lookup/svc/__init__.py
dbpedia_get/lookup/svc/follow_page_links.py
dbpedia_get/lookup/svc/perform_page_lookup.py
dbpedia_get/lookup/svc/perform_page_transform.py
dbpedia_get/recipes/__init__.py
dbpedia_get/recipes/download_categories.py
dbpedia_get/recipes/download_categories_router.py
dbpedia_get/recipes/download_links.py
dbpedia_get/recipes/download_links_router.py
dbpedia_get/recipes/lookup_entity_router.py
dbpedia_get/transform/__init__.py
dbpedia_get/transform/bp/__init__.py
dbpedia_get/transform/bp/transform_orchestrator.py
dbpedia_get/transform/dmo/__init__.py
dbpedia_get/transform/svc/__init__.py
dbpedia_get/transform/svc/transform_categories.py
dbpedia_get/transform/svc/transform_links.py
dbpedia_get-0.1.9.dist-info/WHEEL
dbpedia_get-0.1.9.dist-info/METADATA
dbpedia_get-0.1.9.dist-info/RECORD
